listenbrainz_submit/__init__.py
listenbrainz_submit-1.0.1.dist-info/METADATA
listenbrainz_submit-1.0.1.dist-info/WHEEL
listenbrainz_submit-1.0.1.dist-info/licenses/LICENSE
listenbrainz_submit-1.0.1.dist-info/RECORD
