Metadata-Version: 2.1
Name: listenbrainz_submit
Version: 1.0.1
Summary: Simple client library to submit listens to the ListenBrainz server
Project-URL: Homepage, https://git.sr.ht/~phw/python-listenbrainz-submit
Project-URL: Bug Tracker, https://todo.sr.ht/~phw/python-listenbrainz-submit
Author-email: Philipp Wolfer <ph.wolfer@gmail.com>
License: Copyright (c) 2018-2022 Philipp Wolfer <ph.wolfer@gmail.com>
License-File: LICENSE
Classifier: License :: OSI Approved :: MIT License
Classifier: Operating System :: OS Independent
Classifier: Programming Language :: Python :: 3
Requires-Python: >=3.7
